{
    "profile_heterodimerization_small": {
        "timestamp": 1752701405.3088934,
        "runtime (s)": 83.8917784690857,
        "peak_memory (MB)": 43.019531,
        "flamegraph": "profile_heterodimerization_small_flamegraph.svg",
        "memplot": "profile_heterodimerization_small_memplot.png",
        "memprofile": "profile_heterodimerization_small_memprofile.dat"
    },
    "profile_ktam": {
        "timestamp": 1752701644.834947,
        "runtime (s)": 121.79587459564209,
        "peak_memory (MB)": 31.328125,
        "flamegraph": "profile_ktam_flamegraph.svg",
        "memplot": "profile_ktam_memplot.png",
        "memprofile": "profile_ktam_memprofile.dat"
    },
    "profile_uni_bi_small": {
        "timestamp": 1752701882.874909,
        "runtime (s)": 119.7603452205658,
        "peak_memory (MB)": 31.324219,
        "flamegraph": "profile_uni_bi_small_flamegraph.svg",
        "memplot": "profile_uni_bi_small_memplot.png",
        "memprofile": "profile_uni_bi_small_memprofile.dat"
    }
}