{
    "profile_heterodimerization_small": {
        "timestamp": 1760036205.8674762,
        "runtime (s)": 1.4988367557525635,
        "peak_memory (MB)": 124.664062,
        "flamegraph": "profile_heterodimerization_small_flamegraph.svg",
        "memplot": "profile_heterodimerization_small_memplot.png",
        "memprofile": "profile_heterodimerization_small_memprofile.dat"
    },
    "profile_ktam": {
        "timestamp": 1760036223.1330678,
        "runtime (s)": 8.408360242843628,
        "peak_memory (MB)": 104.347656,
        "flamegraph": "profile_ktam_flamegraph.svg",
        "memplot": "profile_ktam_memplot.png",
        "memprofile": "profile_ktam_memprofile.dat"
    },
    "profile_uni_bi_small": {
        "timestamp": 1760036255.4975548,
        "runtime (s)": 16.280071258544922,
        "peak_memory (MB)": 106.800781,
        "flamegraph": "profile_uni_bi_small_flamegraph.svg",
        "memplot": "profile_uni_bi_small_memplot.png",
        "memprofile": "profile_uni_bi_small_memprofile.dat"
    }
}